colorbleed/__init__.py
colorbleed/action.py
colorbleed/api.py
colorbleed/launcher_actions.py
colorbleed/lib.py
colorbleed/plugin.py
colorbleed/setdress_api.py
colorbleed/version.py
colorbleed/fusion/__init__.py
colorbleed/fusion/lib.py
colorbleed/houdini/__init__.py
colorbleed/houdini/lib.py
colorbleed/maya/__init__.py
colorbleed/maya/action.py
colorbleed/maya/customize.py
colorbleed/maya/lib.py
colorbleed/maya/menu.json
colorbleed/maya/menu.py
colorbleed/maya/plugin.py
colorbleed/plugins/fusion/create/create_tiff_saver.py
colorbleed/plugins/fusion/inventory/select_containers.py
colorbleed/plugins/fusion/inventory/set_tool_color.py
colorbleed/plugins/fusion/load/actions.py
colorbleed/plugins/fusion/load/load_sequence.py
colorbleed/plugins/fusion/publish/collect_comp.py
colorbleed/plugins/fusion/publish/collect_fusion_version.py
colorbleed/plugins/fusion/publish/collect_instances.py
colorbleed/plugins/fusion/publish/collect_render_target.py
colorbleed/plugins/fusion/publish/increment_current_file_deadline.py
colorbleed/plugins/fusion/publish/publish_image_sequences.py
colorbleed/plugins/fusion/publish/render_local.py
colorbleed/plugins/fusion/publish/save_scene.py
colorbleed/plugins/fusion/publish/submit_deadline.py
colorbleed/plugins/fusion/publish/validate_background_depth.py
colorbleed/plugins/fusion/publish/validate_comp_saved.py
colorbleed/plugins/fusion/publish/validate_create_folder_checked.py
colorbleed/plugins/fusion/publish/validate_filename_has_extension.py
colorbleed/plugins/fusion/publish/validate_saver_has_input.py
colorbleed/plugins/fusion/publish/validate_saver_passthrough.py
colorbleed/plugins/fusion/publish/validate_unique_subsets.py
colorbleed/plugins/global/load/copy_file.py
colorbleed/plugins/global/load/copy_file_path.py
colorbleed/plugins/global/load/open_imagesequence.py
colorbleed/plugins/global/publish/cleanup.py
colorbleed/plugins/global/publish/collect_assumed_destination.py
colorbleed/plugins/global/publish/collect_comment.py
avalon_colorbleed-1.0.2.dist-info/METADATA
avalon_colorbleed-1.0.2.dist-info/WHEEL
avalon_colorbleed-1.0.2.dist-info/top_level.txt
avalon_colorbleed-1.0.2.dist-info/RECORD
