Metadata-Version: 2.1
Name: avalon-colorbleed
Version: 1.0.2
Summary: UNKNOWN
Home-page: https://github.com/Colorbleed/colorbleed-config
Author: Roy Nieterau
Author-email: roy@colorbleed.com
License: MIT
Platform: UNKNOWN
Classifier: Development Status :: 5 - Production/Stable
Classifier: License :: OSI Approved :: MIT License
Classifier: Intended Audience :: Developers
Classifier: Operating System :: OS Independent
Classifier: Programming Language :: Python
Classifier: Programming Language :: Python :: 2
Classifier: Programming Language :: Python :: 2.7
Classifier: Programming Language :: Python :: 3
Classifier: Programming Language :: Python :: 3.6
Classifier: Programming Language :: Python :: 3.7
Classifier: Topic :: Utilities
Classifier: Topic :: Software Development
Classifier: Topic :: Software Development :: Libraries :: Python Modules
Requires-Python: >2.7, <4
Requires-Dist: pyblish-base (>=1.5)
Requires-Dist: avalon-core (>=5.2)
